pytora/__init__.py
pytora/lora_layer.py
pytora/utils.py
pytora-0.0.4.dist-info/METADATA
pytora-0.0.4.dist-info/WHEEL
pytora-0.0.4.dist-info/top_level.txt
pytora-0.0.4.dist-info/RECORD
