Metadata-Version: 2.1
Name: pytora
Version: 0.0.4
Summary: A minimal PyTorch implementation of LoRA
Author-email: Lukas Hauzenberger <lukas.hauzenberger@gmail.com>
Classifier: Programming Language :: Python :: 3
Classifier: License :: OSI Approved :: MIT License
Classifier: Operating System :: OS Independent
Requires-Python: >=3.8
Requires-Dist: torch >=1.9.0
